{"_ts":[1519905826],"_r":{"breakdown":{"html":{"bytes":[69201],"requests":[9]},"js":{"bytes":[681526],"requests":[35]},"css":{"bytes":[157803],"requests":[6]},"image":{"bytes":[942076],"requests":[37]},"flash":{"bytes":[0],"requests":[0]},"font":{"bytes":[560189],"requests":[14]},"video":{"bytes":[182851],"requests":[1]},"other":{"bytes":[14791],"requests":[5]}},"date":[1519905826],"domElements":[2041],"domInteractive":[11850],"firstPaint":[0],"fullyLoaded":[18140],"id":["180301_TF_45fd90527862cda4a7489c6ccf3fd832"],"loadTime":[17297],"render":[13000],"SpeedIndex":[13375],"TTFB":[8467],"videoFrames":[[{"_i":"ms_000000.jpg","_t":0,"_vc":0},{"_i":"ms_013000.jpg","_t":13000,"_vc":25},{"_i":"ms_013500.jpg","_t":13500,"_vc":100}]],"visualComplete":[13500],"lighthouse":[null],"pagespeed":[74]}}