{"_ts":[1519873768,1519918284,1519961299],"_r":{"breakdown":{"html":{"bytes":[71931,71954,72009],"requests":[10,10,10]},"js":{"bytes":[670444,670390,670390],"requests":[38,38,38]},"css":{"bytes":[189084,189107,189106],"requests":[8,8,8]},"image":{"bytes":[479618,479599,479692],"requests":[43,43,43]},"flash":{"bytes":[0,0,0],"requests":[0,0,0]},"font":{"bytes":[266956,266956,266956],"requests":[10,10,10]},"video":{"bytes":[182187,182187,182187],"requests":[1,1,1]},"other":{"bytes":[13110,13110,13110],"requests":[11,11,11]}},"date":[1519873768,1519918284,1519961299],"domElements":[2422,2422,2422],"domInteractive":[21473,12559,18059],"firstPaint":[18580,10687.5,15709.199999999],"fullyLoaded":[26949,18176,23655],"id":["180301_1Z_f8461ad9683689fefe181535a5b76323","180301_54_14c0fc45ccdc49456d080805a3317c54","180302_34_4c9211ef090d8859a8ac5889419a3e83"],"loadTime":[23644,14868,20410],"render":[18600,10800,15800],"SpeedIndex":[20738,12096,17365],"TTFB":[17811,10124,15147],"videoFrames":[[{"_i":"ms_000000.jpg","_t":0,"_vc":0},{"_i":"ms_018600.jpg","_t":18600,"_vc":23},{"_i":"ms_018800.jpg","_t":18800,"_vc":23},{"_i":"ms_019100.jpg","_t":19100,"_vc":25},{"_i":"ms_019200.jpg","_t":19200,"_vc":25},{"_i":"ms_020500.jpg","_t":20500,"_vc":25},{"_i":"ms_021400.jpg","_t":21400,"_vc":99},{"_i":"ms_021800.jpg","_t":21800,"_vc":100},{"_i":"ms_021900.jpg","_t":21900,"_vc":99},{"_i":"ms_022100.jpg","_t":22100,"_vc":99},{"_i":"ms_022600.jpg","_t":22600,"_vc":99},{"_i":"ms_023000.jpg","_t":23000,"_vc":99},{"_i":"ms_023300.jpg","_t":23300,"_vc":99},{"_i":"ms_023600.jpg","_t":23600,"_vc":99},{"_i":"ms_023800.jpg","_t":23800,"_vc":99},{"_i":"ms_024200.jpg","_t":24200,"_vc":99},{"_i":"ms_024300.jpg","_t":24300,"_vc":100}],[{"_i":"ms_000000.jpg","_t":0,"_vc":0},{"_i":"ms_010800.jpg","_t":10800,"_vc":23},{"_i":"ms_011000.jpg","_t":11000,"_vc":23},{"_i":"ms_011100.jpg","_t":11100,"_vc":23},{"_i":"ms_011200.jpg","_t":11200,"_vc":25},{"_i":"ms_011300.jpg","_t":11300,"_vc":25},{"_i":"ms_011900.jpg","_t":11900,"_vc":25},{"_i":"ms_012000.jpg","_t":12000,"_vc":25},{"_i":"ms_012500.jpg","_t":12500,"_vc":99},{"_i":"ms_013100.jpg","_t":13100,"_vc":100},{"_i":"ms_014600.jpg","_t":14600,"_vc":99},{"_i":"ms_014800.jpg","_t":14800,"_vc":99},{"_i":"ms_015200.jpg","_t":15200,"_vc":99},{"_i":"ms_015300.jpg","_t":15300,"_vc":100},{"_i":"ms_015401.jpg","_t":15401,"_vc":100}],[{"_i":"ms_000000.jpg","_t":0,"_vc":0},{"_i":"ms_015800.jpg","_t":15800,"_vc":23},{"_i":"ms_015900.jpg","_t":15900,"_vc":24},{"_i":"ms_016100.jpg","_t":16100,"_vc":24},{"_i":"ms_016300.jpg","_t":16300,"_vc":24},{"_i":"ms_016400.jpg","_t":16400,"_vc":25},{"_i":"ms_016500.jpg","_t":16500,"_vc":25},{"_i":"ms_016600.jpg","_t":16600,"_vc":25},{"_i":"ms_016700.jpg","_t":16700,"_vc":34},{"_i":"ms_017500.jpg","_t":17500,"_vc":34},{"_i":"ms_017600.jpg","_t":17600,"_vc":35},{"_i":"ms_018000.jpg","_t":18000,"_vc":99},{"_i":"ms_018100.jpg","_t":18100,"_vc":99},{"_i":"ms_018400.jpg","_t":18400,"_vc":99},{"_i":"ms_018500.jpg","_t":18500,"_vc":99},{"_i":"ms_018600.jpg","_t":18600,"_vc":99},{"_i":"ms_018900.jpg","_t":18900,"_vc":99},{"_i":"ms_019000.jpg","_t":19000,"_vc":99},{"_i":"ms_019800.jpg","_t":19800,"_vc":99},{"_i":"ms_019900.jpg","_t":19900,"_vc":100},{"_i":"ms_020000.jpg","_t":20000,"_vc":99},{"_i":"ms_020200.jpg","_t":20200,"_vc":99},{"_i":"ms_020900.jpg","_t":20900,"_vc":99},{"_i":"ms_021000.jpg","_t":21000,"_vc":100}]],"visualComplete":[21800,13100,19900],"lighthouse":[54,54,54],"pagespeed":[70,69,70]}}