{"_ts":[1525147841,1525192041],"_r":{"breakdown":{"html":{"bytes":[73922,74589],"requests":[10,13]},"js":{"bytes":[579410,579397],"requests":[33,33]},"css":{"bytes":[189394,189394],"requests":[8,8]},"image":{"bytes":[481367,482984],"requests":[42,44]},"flash":{"bytes":[0,0],"requests":[0,0]},"font":{"bytes":[251769,251769],"requests":[9,9]},"video":{"bytes":[182187,182187],"requests":[1,1]},"other":{"bytes":[13128,13110],"requests":[11,12]}},"date":[1525147841,1525192041],"domElements":[2427,2427],"domInteractive":[13806,16110],"firstPaint":[11213.100000001,13482.600000003],"fullyLoaded":[17922,18172],"id":["180501_ST_ce9df4f11f285b7f9e0901c10cf39615","180501_VC_0ededbabae6a3fbe3a81ebc8fb9573a9"],"loadTime":[15135,17784],"render":[11200,13500],"SpeedIndex":[12607,14743],"TTFB":[10403,12712],"videoFrames":[[{"_i":"ms_000000.jpg","_t":0,"_vc":0},{"_i":"ms_011200.jpg","_t":11200,"_vc":23},{"_i":"ms_011400.jpg","_t":11400,"_vc":24},{"_i":"ms_011600.jpg","_t":11600,"_vc":26},{"_i":"ms_011700.jpg","_t":11700,"_vc":26},{"_i":"ms_011800.jpg","_t":11800,"_vc":25},{"_i":"ms_011900.jpg","_t":11900,"_vc":25},{"_i":"ms_012400.jpg","_t":12400,"_vc":56},{"_i":"ms_013000.jpg","_t":13000,"_vc":56},{"_i":"ms_013500.jpg","_t":13500,"_vc":99},{"_i":"ms_014100.jpg","_t":14100,"_vc":99},{"_i":"ms_014300.jpg","_t":14300,"_vc":99},{"_i":"ms_014500.jpg","_t":14500,"_vc":99},{"_i":"ms_014700.jpg","_t":14700,"_vc":99},{"_i":"ms_015000.jpg","_t":15000,"_vc":99},{"_i":"ms_015400.jpg","_t":15400,"_vc":100},{"_i":"ms_015500.jpg","_t":15500,"_vc":100}],[{"_i":"ms_000000.jpg","_t":0,"_vc":0},{"_i":"ms_013500.jpg","_t":13500,"_vc":22},{"_i":"ms_013600.jpg","_t":13600,"_vc":23},{"_i":"ms_013800.jpg","_t":13800,"_vc":24},{"_i":"ms_013900.jpg","_t":13900,"_vc":23},{"_i":"ms_014000.jpg","_t":14000,"_vc":23},{"_i":"ms_014200.jpg","_t":14200,"_vc":25},{"_i":"ms_014300.jpg","_t":14300,"_vc":26},{"_i":"ms_014400.jpg","_t":14400,"_vc":56},{"_i":"ms_014500.jpg","_t":14500,"_vc":56},{"_i":"ms_015600.jpg","_t":15600,"_vc":99},{"_i":"ms_015800.jpg","_t":15800,"_vc":99},{"_i":"ms_016100.jpg","_t":16100,"_vc":99},{"_i":"ms_016500.jpg","_t":16500,"_vc":99},{"_i":"ms_016600.jpg","_t":16600,"_vc":99},{"_i":"ms_016800.jpg","_t":16800,"_vc":99},{"_i":"ms_017100.jpg","_t":17100,"_vc":99},{"_i":"ms_017300.jpg","_t":17300,"_vc":99},{"_i":"ms_017800.jpg","_t":17800,"_vc":99},{"_i":"ms_018100.jpg","_t":18100,"_vc":99},{"_i":"ms_018200.jpg","_t":18200,"_vc":99},{"_i":"ms_018300.jpg","_t":18300,"_vc":100}]],"visualComplete":[15400,18300],"lighthouse":[54,54],"pagespeed":[70,70]}}