{"_ts":[1506409716],"_r":{"breakdown":{"html":{"bytes":[2729],"requests":[4]},"js":{"bytes":[907800],"requests":[28]},"css":{"bytes":[138411],"requests":[8]},"image":{"bytes":[3782136],"requests":[74]},"flash":{"bytes":[0],"requests":[0]},"font":{"bytes":[52551],"requests":[3]},"other":{"bytes":[4786845],"requests":[6]}},"date":[1506409716],"domElements":[1837],"domInteractive":[15761],"firstPaint":[13116],"fullyLoaded":[30704],"id":["170926_4Y_84d21bb1028de92902c51ea95b7e54f2"],"loadTime":[29525],"render":[13497],"SpeedIndex":[19262],"TTFB":[10378],"videoFrames":[[{"_i":"frame_0000.jpg","_t":0,"_vc":0},{"_i":"frame_0135.jpg","_t":13500,"_vc":5},{"_i":"frame_0137.jpg","_t":13700,"_vc":5},{"_i":"frame_0152.jpg","_t":15200,"_vc":6},{"_i":"frame_0176.jpg","_t":17600,"_vc":6},{"_i":"frame_0180.jpg","_t":18000,"_vc":36},{"_i":"frame_0186.jpg","_t":18600,"_vc":60},{"_i":"frame_0196.jpg","_t":19600,"_vc":69},{"_i":"frame_0204.jpg","_t":20400,"_vc":78},{"_i":"frame_0214.jpg","_t":21400,"_vc":86},{"_i":"frame_0224.jpg","_t":22400,"_vc":91},{"_i":"frame_0234.jpg","_t":23400,"_vc":99},{"_i":"frame_0244.jpg","_t":24400,"_vc":99},{"_i":"frame_0254.jpg","_t":25400,"_vc":99},{"_i":"frame_0264.jpg","_t":26400,"_vc":99},{"_i":"frame_0267.jpg","_t":26700,"_vc":100}]],"visualComplete":[26700],"lighthouse":[null],"pagespeed":[40]}}