{"_ts":[1564619667],"_r":{"breakdown":{"html":{"bytes":[75596],"requests":[26]},"js":{"bytes":[1241180],"requests":[57]},"css":{"bytes":[160447],"requests":[6]},"image":{"bytes":[395901],"requests":[78]},"flash":{"bytes":[0],"requests":[0]},"font":{"bytes":[179568],"requests":[7]},"video":{"bytes":[0],"requests":[0]},"other":{"bytes":[8484],"requests":[13]}},"date":[1564619667],"domElements":[1343],"domInteractive":[3926],"firstPaint":[5407.0900000006],"fullyLoaded":[8554],"id":["190801_W8_9b27b26fdafb7c27b96bf6599e17c9f7"],"loadTime":[7079],"render":[5400],"SpeedIndex":[5439],"TTFB":[560],"videoFrames":[[{"_i":"ms_000000.jpg","_t":0,"_vc":0},{"_i":"ms_005400.jpg","_t":5400,"_vc":95},{"_i":"ms_006000.jpg","_t":6000,"_vc":95},{"_i":"ms_006100.jpg","_t":6100,"_vc":96},{"_i":"ms_006200.jpg","_t":6200,"_vc":100}]],"visualComplete":[6200],"lighthouse":[23],"pagespeed":[62]}}