{"_ts":[1556679093,1556723284],"_r":{"breakdown":{"html":{"bytes":[114255,115223],"requests":[6,8]},"js":{"bytes":[738205,738242],"requests":[36,36]},"css":{"bytes":[163277,163277],"requests":[6,6]},"image":{"bytes":[398957,398941],"requests":[31,31]},"flash":{"bytes":[0,0],"requests":[0,0]},"font":{"bytes":[286444,286444],"requests":[8,8]},"video":{"bytes":[452140,452140],"requests":[1,1]},"other":{"bytes":[21347,21285],"requests":[24,24]}},"date":[1556679093,1556723284],"domElements":[2208,2209],"domInteractive":[3592,3321],"firstPaint":[1120.1849999998,1095.9000000003],"fullyLoaded":[44240,8981],"id":["190501_TV_950ab2306839843ef69ed26291f94a49","190501_D2_2f106c3dacfbed0c1a9c3e65f60e63a8"],"loadTime":[43251,7244],"render":[1100,1100],"SpeedIndex":[1968,1634],"TTFB":[369,402],"videoFrames":[[{"_i":"ms_000000.jpg","_t":0,"_vc":0},{"_i":"ms_001100.jpg","_t":1100,"_vc":13},{"_i":"ms_001200.jpg","_t":1200,"_vc":13},{"_i":"ms_001300.jpg","_t":1300,"_vc":14},{"_i":"ms_001500.jpg","_t":1500,"_vc":16},{"_i":"ms_001700.jpg","_t":1700,"_vc":15},{"_i":"ms_002100.jpg","_t":2100,"_vc":99},{"_i":"ms_002600.jpg","_t":2600,"_vc":99},{"_i":"ms_002700.jpg","_t":2700,"_vc":99},{"_i":"ms_003000.jpg","_t":3000,"_vc":100},{"_i":"ms_003300.jpg","_t":3300,"_vc":100},{"_i":"ms_003500.jpg","_t":3500,"_vc":99},{"_i":"ms_003800.jpg","_t":3800,"_vc":99},{"_i":"ms_004000.jpg","_t":4000,"_vc":100}],[{"_i":"ms_000000.jpg","_t":0,"_vc":0},{"_i":"ms_001100.jpg","_t":1100,"_vc":14},{"_i":"ms_001200.jpg","_t":1200,"_vc":14},{"_i":"ms_001400.jpg","_t":1400,"_vc":14},{"_i":"ms_001700.jpg","_t":1700,"_vc":98},{"_i":"ms_001900.jpg","_t":1900,"_vc":99},{"_i":"ms_002100.jpg","_t":2100,"_vc":99},{"_i":"ms_002400.jpg","_t":2400,"_vc":99},{"_i":"ms_003000.jpg","_t":3000,"_vc":100},{"_i":"ms_003100.jpg","_t":3100,"_vc":100},{"_i":"ms_003200.jpg","_t":3200,"_vc":99},{"_i":"ms_003500.jpg","_t":3500,"_vc":100},{"_i":"ms_003600.jpg","_t":3600,"_vc":100}]],"visualComplete":[3000,3000],"lighthouse":[null,31],"pagespeed":[73,73]}}