{"_ts":[1567298293],"_r":{"breakdown":{"html":{"bytes":[303786],"requests":[8]},"js":{"bytes":[527040],"requests":[34]},"css":{"bytes":[163790],"requests":[6]},"image":{"bytes":[1506225],"requests":[29]},"flash":{"bytes":[0],"requests":[0]},"font":{"bytes":[286444],"requests":[8]},"video":{"bytes":[698044],"requests":[1]},"other":{"bytes":[21231],"requests":[21]}},"date":[1567298293],"domElements":[2071],"domInteractive":[1884],"firstPaint":[1183.7100000048],"fullyLoaded":[7666],"id":["190901_NT_70248d087c975ee10a623e42f02614d8"],"loadTime":[6494],"render":[1200],"SpeedIndex":[2305],"TTFB":[419],"videoFrames":[[{"_i":"ms_000000.jpg","_t":0,"_vc":0},{"_i":"ms_001200.jpg","_t":1200,"_vc":21},{"_i":"ms_001300.jpg","_t":1300,"_vc":23},{"_i":"ms_001600.jpg","_t":1600,"_vc":21},{"_i":"ms_001800.jpg","_t":1800,"_vc":22},{"_i":"ms_002300.jpg","_t":2300,"_vc":22},{"_i":"ms_002600.jpg","_t":2600,"_vc":99},{"_i":"ms_003900.jpg","_t":3900,"_vc":100}]],"visualComplete":[3900],"lighthouse":[31],"pagespeed":[46]}}