{"_ts":[1543642479],"_r":{"breakdown":{"html":{"bytes":[65798],"requests":[5]},"js":{"bytes":[311393],"requests":[20]},"css":{"bytes":[68896],"requests":[4]},"image":{"bytes":[164942],"requests":[26]},"flash":{"bytes":[0],"requests":[0]},"font":{"bytes":[231364],"requests":[8]},"video":{"bytes":[0],"requests":[0]},"other":{"bytes":[6439],"requests":[8]}},"date":[1543642479],"domElements":[1460],"domInteractive":[5579],"firstPaint":[4828.6999999982],"fullyLoaded":[6955],"id":["181201_9A_a87a8f1a1ab8fef946e20a7fa89db739"],"loadTime":[6586],"render":[4900],"SpeedIndex":[5856],"TTFB":[3631],"videoFrames":[[{"_i":"ms_000000.jpg","_t":0,"_vc":0},{"_i":"ms_004900.jpg","_t":4900,"_vc":25},{"_i":"ms_005000.jpg","_t":5000,"_vc":25},{"_i":"ms_005300.jpg","_t":5300,"_vc":24},{"_i":"ms_005400.jpg","_t":5400,"_vc":26},{"_i":"ms_005500.jpg","_t":5500,"_vc":29},{"_i":"ms_005600.jpg","_t":5600,"_vc":29},{"_i":"ms_005800.jpg","_t":5800,"_vc":29},{"_i":"ms_005900.jpg","_t":5900,"_vc":29},{"_i":"ms_006000.jpg","_t":6000,"_vc":29},{"_i":"ms_006200.jpg","_t":6200,"_vc":92},{"_i":"ms_006300.jpg","_t":6300,"_vc":99},{"_i":"ms_006400.jpg","_t":6400,"_vc":100}]],"visualComplete":[6400],"lighthouse":[31],"pagespeed":[59]}}