{"_ts":[1519874214],"_r":{"breakdown":{"html":{"bytes":[198410],"requests":[6]},"js":{"bytes":[566288],"requests":[31]},"css":{"bytes":[68918],"requests":[5]},"image":{"bytes":[397053],"requests":[32]},"flash":{"bytes":[0],"requests":[0]},"font":{"bytes":[184307],"requests":[7]},"video":{"bytes":[598246],"requests":[2]},"other":{"bytes":[25810],"requests":[11]}},"date":[1519874214],"domElements":[1974],"domInteractive":[13286],"firstPaint":[11749.1],"fullyLoaded":[19133],"id":["180301_EA_96963bd4ad63dd19c1d6197722284d15"],"loadTime":[14939],"render":[11800],"SpeedIndex":[12481],"TTFB":[11094],"videoFrames":[[{"_i":"ms_000000.jpg","_t":0,"_vc":0},{"_i":"ms_011800.jpg","_t":11800,"_vc":13},{"_i":"ms_011900.jpg","_t":11900,"_vc":12},{"_i":"ms_012100.jpg","_t":12100,"_vc":18},{"_i":"ms_012200.jpg","_t":12200,"_vc":18},{"_i":"ms_012400.jpg","_t":12400,"_vc":18},{"_i":"ms_012500.jpg","_t":12500,"_vc":18},{"_i":"ms_012600.jpg","_t":12600,"_vc":99},{"_i":"ms_013300.jpg","_t":13300,"_vc":99},{"_i":"ms_013400.jpg","_t":13400,"_vc":100},{"_i":"ms_013600.jpg","_t":13600,"_vc":100},{"_i":"ms_014100.jpg","_t":14100,"_vc":100},{"_i":"ms_014400.jpg","_t":14400,"_vc":100},{"_i":"ms_014600.jpg","_t":14600,"_vc":100},{"_i":"ms_014900.jpg","_t":14900,"_vc":100},{"_i":"ms_015200.jpg","_t":15200,"_vc":100},{"_i":"ms_015300.jpg","_t":15300,"_vc":100},{"_i":"ms_015401.jpg","_t":15401,"_vc":100}]],"visualComplete":[13400],"lighthouse":[54],"pagespeed":[52]}}