{"_ts":[1512109608,1512153383,1512197607],"_r":{"breakdown":{"html":{"bytes":[105779,105680,106076],"requests":[2,2,2]},"js":{"bytes":[1054358,1424169,1424208],"requests":[24,43,43]},"css":{"bytes":[553277,553277,553277],"requests":[4,4,4]},"image":{"bytes":[816178,816178,816179],"requests":[47,47,47]},"flash":{"bytes":[0,0,0],"requests":[0,0,0]},"font":{"bytes":[133768,133768,133768],"requests":[4,4,4]},"video":{"bytes":[0,0,0],"requests":[0,0,0]},"other":{"bytes":[6723,6728,6721],"requests":[2,2,2]}},"date":[1512109608,1512153383,1512197607],"domElements":[1332,1351,1351],"domInteractive":[3318,8562,4131],"firstPaint":[4593,9518,5418],"fullyLoaded":[10452,15729,11405],"id":["171201_AG_9539b0eafefb42b6953996fd31e0fab2","171201_WT_561ee98637a0969df9b961594d3b0b70","171202_RH_0147f1b3233353e4e0142456ffa1a670"],"loadTime":[6584,11426,6966],"render":[4711,9590,5583],"SpeedIndex":[5246,10134,6134],"TTFB":[301,4581,700],"videoFrames":[[{"_i":"frame_0000.jpg","_t":0,"_vc":0},{"_i":"frame_0047.jpg","_t":4700,"_vc":10},{"_i":"frame_0049.jpg","_t":4900,"_vc":12},{"_i":"frame_0052.jpg","_t":5200,"_vc":83},{"_i":"frame_0058.jpg","_t":5800,"_vc":100}],[{"_i":"frame_0000.jpg","_t":0,"_vc":0},{"_i":"frame_0096.jpg","_t":9600,"_vc":10},{"_i":"frame_0099.jpg","_t":9900,"_vc":12},{"_i":"frame_0102.jpg","_t":10200,"_vc":100}],[{"_i":"frame_0000.jpg","_t":0,"_vc":0},{"_i":"frame_0056.jpg","_t":5600,"_vc":11},{"_i":"frame_0059.jpg","_t":5900,"_vc":12},{"_i":"frame_0062.jpg","_t":6200,"_vc":99},{"_i":"frame_0064.jpg","_t":6400,"_vc":99},{"_i":"frame_0065.jpg","_t":6500,"_vc":100}]],"visualComplete":[5800,10200,6500],"lighthouse":[null,null,null],"pagespeed":[47,43,35]}}