{"_ts":[1519874225],"_r":{"breakdown":{"html":{"bytes":[78042],"requests":[9]},"js":{"bytes":[683440],"requests":[37]},"css":{"bytes":[190187],"requests":[8]},"image":{"bytes":[1074634],"requests":[40]},"flash":{"bytes":[0],"requests":[0]},"font":{"bytes":[1050403],"requests":[24]},"video":{"bytes":[182851],"requests":[1]},"other":{"bytes":[14845],"requests":[5]}},"date":[1519874225],"domElements":[2703],"domInteractive":[17619],"firstPaint":[0],"fullyLoaded":[23137],"id":["180301_KM_3d35f7a97d6b6a1a4479b2715fc5dc09"],"loadTime":[20594],"render":[18300],"SpeedIndex":[18300],"TTFB":[11778],"videoFrames":[[{"_i":"ms_000000.jpg","_t":0,"_vc":0},{"_i":"ms_018300.jpg","_t":18300,"_vc":100}]],"visualComplete":[18300],"lighthouse":[null],"pagespeed":[62]}}