{"_ts":[1572567569,1572611057],"_r":{"breakdown":{"html":{"bytes":[301749,301907],"requests":[8,8]},"js":{"bytes":[578224,578224],"requests":[35,35]},"css":{"bytes":[164700,164700],"requests":[6,6]},"image":{"bytes":[483771,483813],"requests":[30,30]},"flash":{"bytes":[0,0],"requests":[0,0]},"font":{"bytes":[286444,286444],"requests":[8,8]},"video":{"bytes":[698044,698044],"requests":[1,1]},"other":{"bytes":[18117,16154],"requests":[16,14]}},"date":[1572567569,1572611057],"domElements":[2019,2019],"domInteractive":[5844,7030],"firstPaint":[4792.2350000008,6375.1399999965],"fullyLoaded":[11474,12627],"id":["191101_JS_c1ac10a1b6b2541f8a79708d975b99c6","191101_EM_cba70ee43775430963ffa2fa4452c61e"],"loadTime":[9049,10178],"render":[4800,6300],"SpeedIndex":[6007,7216],"TTFB":[3949,5639],"videoFrames":[[{"_i":"ms_000000.jpg","_t":0,"_vc":0},{"_i":"ms_004800.jpg","_t":4800,"_vc":23},{"_i":"ms_005000.jpg","_t":5000,"_vc":23},{"_i":"ms_005200.jpg","_t":5200,"_vc":24},{"_i":"ms_005300.jpg","_t":5300,"_vc":24},{"_i":"ms_005400.jpg","_t":5400,"_vc":24},{"_i":"ms_005600.jpg","_t":5600,"_vc":25},{"_i":"ms_005700.jpg","_t":5700,"_vc":27},{"_i":"ms_006400.jpg","_t":6400,"_vc":99},{"_i":"ms_007300.jpg","_t":7300,"_vc":100},{"_i":"ms_007400.jpg","_t":7400,"_vc":100}],[{"_i":"ms_000000.jpg","_t":0,"_vc":0},{"_i":"ms_006300.jpg","_t":6300,"_vc":23},{"_i":"ms_006500.jpg","_t":6500,"_vc":24},{"_i":"ms_006800.jpg","_t":6800,"_vc":24},{"_i":"ms_007000.jpg","_t":7000,"_vc":27},{"_i":"ms_007100.jpg","_t":7100,"_vc":27},{"_i":"ms_007200.jpg","_t":7200,"_vc":27},{"_i":"ms_007400.jpg","_t":7400,"_vc":85},{"_i":"ms_008000.jpg","_t":8000,"_vc":100}]],"visualComplete":[7300,8000],"lighthouse":[31,31],"pagespeed":[71,71]}}