{"_ts":[1509496971,1509540172,1509584211,1509628314,1509671660,1509758311,1509802410],"_r":{"breakdown":{"html":{"bytes":[11690,16600,16600,11690,15030,10521,11690],"requests":[10,10,10,10,10,9,10]},"js":{"bytes":[658265,657995,352075,658391,349722,658342,658291],"requests":[21,21,21,21,21,21,21]},"css":{"bytes":[66129,299858,79481,66129,78225,66129,66129],"requests":[9,9,9,9,9,9,9]},"image":{"bytes":[4995598,4994885,4994885,4995598,4987576,4995598,4995598],"requests":[32,32,32,32,32,32,32]},"flash":{"bytes":[0,0,0,0,0,0,0],"requests":[0,0,0,0,0,0,0]},"font":{"bytes":[229140,228933,228933,229140,227520,229140,229140],"requests":[9,9,9,9,9,9,9]},"video":{"bytes":[0,0,0,0,0,0,0],"requests":[0,0,0,0,0,0,0]},"other":{"bytes":[1950,0,0,1950,0,0,1949],"requests":[1,0,0,1,0,0,1]}},"date":[1509496971,1509540172,1509584211,1509628314,1509671660,1509758311,1509802410],"domElements":[1522,1522,1522,1522,1522,1522,1522],"domInteractive":[7941,8533,8556,7132,12706,8220,9427],"firstPaint":[7994,8670,8588,7176,13177,8720,9445],"fullyLoaded":[16390,18288,17909,17175,20988,17181,16832],"id":["171101_3F_7b8dd6e7b0988100a6039c40c2de0ba0","171101_Q1_bd5f81c8990dbeada872efa7ede9c000","171102_PW_bdfcb8ae729e1cab798ab51f568521cb","171102_1E_a1459895bac8c0a5a322fd45c5a6c0df","171103_BR_c7b443fc2e12732fd6a3f11374bfa19b","171104_ZS_8b56780a69b89fcd7ce54896abf1bb11","171104_GP_bd2b6a88e6a8e4686b02fb3159a149d1"],"loadTime":[16313,18115,17805,17090,20910,17105,16746],"render":[8187,8704,8699,7287,13380,8806,9683],"SpeedIndex":[9532,10419,9813,9459,15282,10014,11134],"TTFB":[5139,5039,5606,5025,4574,4963,5267],"videoFrames":[[{"_i":"frame_0000.jpg","_t":0,"_vc":0},{"_i":"frame_0082.jpg","_t":8200,"_vc":28},{"_i":"frame_0088.jpg","_t":8800,"_vc":37},{"_i":"frame_0092.jpg","_t":9200,"_vc":48},{"_i":"frame_0101.jpg","_t":10100,"_vc":82},{"_i":"frame_0111.jpg","_t":11100,"_vc":100}],[{"_i":"frame_0000.jpg","_t":0,"_vc":0},{"_i":"frame_0087.jpg","_t":8700,"_vc":36},{"_i":"frame_0094.jpg","_t":9400,"_vc":36},{"_i":"frame_0097.jpg","_t":9700,"_vc":38},{"_i":"frame_0098.jpg","_t":9800,"_vc":38},{"_i":"frame_0100.jpg","_t":10000,"_vc":43},{"_i":"frame_0109.jpg","_t":10900,"_vc":76},{"_i":"frame_0119.jpg","_t":11900,"_vc":86},{"_i":"frame_0129.jpg","_t":12900,"_vc":100}],[{"_i":"frame_0000.jpg","_t":0,"_vc":0},{"_i":"frame_0087.jpg","_t":8700,"_vc":36},{"_i":"frame_0091.jpg","_t":9100,"_vc":37},{"_i":"frame_0093.jpg","_t":9300,"_vc":38},{"_i":"frame_0094.jpg","_t":9400,"_vc":43},{"_i":"frame_0096.jpg","_t":9600,"_vc":43},{"_i":"frame_0104.jpg","_t":10400,"_vc":89},{"_i":"frame_0113.jpg","_t":11300,"_vc":100}],[{"_i":"frame_0000.jpg","_t":0,"_vc":0},{"_i":"frame_0073.jpg","_t":7300,"_vc":28},{"_i":"frame_0078.jpg","_t":7800,"_vc":28},{"_i":"frame_0080.jpg","_t":8000,"_vc":36},{"_i":"frame_0089.jpg","_t":8900,"_vc":36},{"_i":"frame_0091.jpg","_t":9100,"_vc":37},{"_i":"frame_0093.jpg","_t":9300,"_vc":43},{"_i":"frame_0095.jpg","_t":9500,"_vc":43},{"_i":"frame_0104.jpg","_t":10400,"_vc":82},{"_i":"frame_0115.jpg","_t":11500,"_vc":100}],[{"_i":"frame_0000.jpg","_t":0,"_vc":0},{"_i":"frame_0134.jpg","_t":13400,"_vc":36},{"_i":"frame_0136.jpg","_t":13600,"_vc":38},{"_i":"frame_0138.jpg","_t":13800,"_vc":38},{"_i":"frame_0140.jpg","_t":14000,"_vc":38},{"_i":"frame_0142.jpg","_t":14200,"_vc":42},{"_i":"frame_0143.jpg","_t":14300,"_vc":42},{"_i":"frame_0145.jpg","_t":14500,"_vc":42},{"_i":"frame_0151.jpg","_t":15100,"_vc":42},{"_i":"frame_0156.jpg","_t":15600,"_vc":43},{"_i":"frame_0166.jpg","_t":16600,"_vc":100}],[{"_i":"frame_0000.jpg","_t":0,"_vc":0},{"_i":"frame_0088.jpg","_t":8800,"_vc":28},{"_i":"frame_0091.jpg","_t":9100,"_vc":36},{"_i":"frame_0092.jpg","_t":9200,"_vc":37},{"_i":"frame_0093.jpg","_t":9300,"_vc":37},{"_i":"frame_0099.jpg","_t":9900,"_vc":39},{"_i":"frame_0101.jpg","_t":10100,"_vc":76},{"_i":"frame_0109.jpg","_t":10900,"_vc":76},{"_i":"frame_0111.jpg","_t":11100,"_vc":94},{"_i":"frame_0112.jpg","_t":11200,"_vc":95},{"_i":"frame_0121.jpg","_t":12100,"_vc":96},{"_i":"frame_0131.jpg","_t":13100,"_vc":96},{"_i":"frame_0141.jpg","_t":14100,"_vc":100}],[{"_i":"frame_0000.jpg","_t":0,"_vc":0},{"_i":"frame_0097.jpg","_t":9700,"_vc":36},{"_i":"frame_0101.jpg","_t":10100,"_vc":36},{"_i":"frame_0104.jpg","_t":10400,"_vc":38},{"_i":"frame_0105.jpg","_t":10500,"_vc":42},{"_i":"frame_0106.jpg","_t":10600,"_vc":42},{"_i":"frame_0108.jpg","_t":10800,"_vc":42},{"_i":"frame_0118.jpg","_t":11800,"_vc":83},{"_i":"frame_0124.jpg","_t":12400,"_vc":83},{"_i":"frame_0127.jpg","_t":12700,"_vc":83},{"_i":"frame_0128.jpg","_t":12800,"_vc":100}]],"visualComplete":[11100,12900,11300,11500,16600,14100,12800],"lighthouse":[null,null,null,null,null,null,null],"pagespeed":[13,12,10,11,13,11,11]}}