{"_ts":[1549003470],"_r":{"breakdown":{"html":{"bytes":[112097],"requests":[4]},"js":{"bytes":[709854],"requests":[34]},"css":{"bytes":[164995],"requests":[6]},"image":{"bytes":[522614],"requests":[34]},"flash":{"bytes":[0],"requests":[0]},"font":{"bytes":[735073],"requests":[18]},"video":{"bytes":[443782],"requests":[1]},"other":{"bytes":[19269],"requests":[8]}},"date":[1549003470],"domElements":[2130],"domInteractive":[4145],"firstPaint":[0],"fullyLoaded":[21665],"id":["190201_3K_92acaad383a85eb0aabfe26bf8fe4d49"],"loadTime":[7560],"render":[6000],"SpeedIndex":[6201],"TTFB":[185],"videoFrames":[[{"_i":"ms_000000.jpg","_t":0,"_vc":0},{"_i":"ms_006000.jpg","_t":6000,"_vc":33},{"_i":"ms_006300.jpg","_t":6300,"_vc":100}]],"visualComplete":[6300],"lighthouse":[null],"pagespeed":[77]}}