{"_ts":[1567297057,1567341086],"_r":{"breakdown":{"html":{"bytes":[303455,303420],"requests":[8,8]},"js":{"bytes":[472507,472479],"requests":[31,31]},"css":{"bytes":[163790,163790],"requests":[6,6]},"image":{"bytes":[418594,509119],"requests":[30,30]},"flash":{"bytes":[0,0],"requests":[0,0]},"font":{"bytes":[286444,286444],"requests":[8,8]},"video":{"bytes":[698044,698044],"requests":[1,1]},"other":{"bytes":[21161,21101],"requests":[20,19]}},"date":[1567297057,1567341086],"domElements":[2129,2129],"domInteractive":[2397,2384],"firstPaint":[1498.8099999973,1392.9349999999],"fullyLoaded":[6679,6733],"id":["190901_RT_55a95acac4e2240c273e3ea8fd15908b","190901_7F_b5e22e0a6ed9ebfbc527a45b50da0093"],"loadTime":[5182,5184],"render":[1500,1400],"SpeedIndex":[2028,2005],"TTFB":[719,649],"videoFrames":[[{"_i":"ms_000000.jpg","_t":0,"_vc":0},{"_i":"ms_001500.jpg","_t":1500,"_vc":22},{"_i":"ms_001600.jpg","_t":1600,"_vc":37},{"_i":"ms_002000.jpg","_t":2000,"_vc":38},{"_i":"ms_002100.jpg","_t":2100,"_vc":38},{"_i":"ms_002200.jpg","_t":2200,"_vc":41},{"_i":"ms_002300.jpg","_t":2300,"_vc":99},{"_i":"ms_003800.jpg","_t":3800,"_vc":100}],[{"_i":"ms_000000.jpg","_t":0,"_vc":0},{"_i":"ms_001400.jpg","_t":1400,"_vc":23},{"_i":"ms_001600.jpg","_t":1600,"_vc":37},{"_i":"ms_002100.jpg","_t":2100,"_vc":37},{"_i":"ms_002200.jpg","_t":2200,"_vc":38},{"_i":"ms_002300.jpg","_t":2300,"_vc":99},{"_i":"ms_003400.jpg","_t":3400,"_vc":100}]],"visualComplete":[3800,3400],"lighthouse":[31,31],"pagespeed":[75,71]}}