{"_ts":[1506377975,1506452950],"_r":{"breakdown":{"html":{"bytes":[2754,2729],"requests":[4,4]},"js":{"bytes":[907807,907853],"requests":[28,28]},"css":{"bytes":[138411,138411],"requests":[8,8]},"image":{"bytes":[3971721,3971779],"requests":[79,79]},"flash":{"bytes":[0,0],"requests":[0,0]},"font":{"bytes":[52551,52551],"requests":[3,3]},"other":{"bytes":[4778654,4786673],"requests":[6,6]}},"date":[1506377975,1506452950],"domElements":[1970,1970],"domInteractive":[21568,28811],"firstPaint":[16799,24914],"fullyLoaded":[32905,40652],"id":["170925_V3_c16b4d202e8a6c6b26248a497741ab21","170926_RY_8b0266a4bd819ffb05a90824291cbd9d"],"loadTime":[29640,36084],"render":[16985,25503],"SpeedIndex":[22147,30211],"TTFB":[13986,20345],"videoFrames":[[{"_i":"frame_0000.jpg","_t":0,"_vc":0},{"_i":"frame_0167.jpg","_t":16700,"_vc":0},{"_i":"frame_0170.jpg","_t":17000,"_vc":0},{"_i":"frame_0172.jpg","_t":17200,"_vc":5},{"_i":"frame_0178.jpg","_t":17800,"_vc":5},{"_i":"frame_0202.jpg","_t":20200,"_vc":20},{"_i":"frame_0203.jpg","_t":20300,"_vc":20},{"_i":"frame_0223.jpg","_t":22300,"_vc":62},{"_i":"frame_0226.jpg","_t":22600,"_vc":86},{"_i":"frame_0227.jpg","_t":22700,"_vc":65},{"_i":"frame_0235.jpg","_t":23500,"_vc":93},{"_i":"frame_0236.jpg","_t":23600,"_vc":99},{"_i":"frame_0241.jpg","_t":24100,"_vc":100},{"_i":"frame_0246.jpg","_t":24600,"_vc":97},{"_i":"frame_0255.jpg","_t":25500,"_vc":99},{"_i":"frame_0265.jpg","_t":26500,"_vc":99},{"_i":"frame_0289.jpg","_t":28900,"_vc":99},{"_i":"frame_0298.jpg","_t":29800,"_vc":100}],[{"_i":"frame_0000.jpg","_t":0,"_vc":0},{"_i":"frame_0255.jpg","_t":25500,"_vc":5},{"_i":"frame_0257.jpg","_t":25700,"_vc":6},{"_i":"frame_0273.jpg","_t":27300,"_vc":20},{"_i":"frame_0292.jpg","_t":29200,"_vc":42},{"_i":"frame_0298.jpg","_t":29800,"_vc":61},{"_i":"frame_0308.jpg","_t":30800,"_vc":72},{"_i":"frame_0319.jpg","_t":31900,"_vc":80},{"_i":"frame_0329.jpg","_t":32900,"_vc":85},{"_i":"frame_0335.jpg","_t":33500,"_vc":89},{"_i":"frame_0345.jpg","_t":34500,"_vc":96},{"_i":"frame_0355.jpg","_t":35500,"_vc":99},{"_i":"frame_0366.jpg","_t":36600,"_vc":100}]],"visualComplete":[29800,36600],"lighthouse":[null,null],"pagespeed":[37,38]}}