{"_ts":[1546312560],"_r":{"breakdown":{"html":{"bytes":[96373],"requests":[5]},"js":{"bytes":[670558],"requests":[31]},"css":{"bytes":[164123],"requests":[6]},"image":{"bytes":[237643],"requests":[30]},"flash":{"bytes":[0],"requests":[0]},"font":{"bytes":[313710],"requests":[10]},"video":{"bytes":[442567],"requests":[1]},"other":{"bytes":[20222],"requests":[14]}},"date":[1546312560],"domElements":[2117],"domInteractive":[14017],"firstPaint":[12381.3999999984],"fullyLoaded":[24339],"id":["190101_F0_4ffaa9b932f2d431fae509868d8858c5"],"loadTime":[24208],"render":[12400],"SpeedIndex":[13321],"TTFB":[11287],"videoFrames":[[{"_i":"ms_000000.jpg","_t":0,"_vc":0},{"_i":"ms_012400.jpg","_t":12400,"_vc":14},{"_i":"ms_012600.jpg","_t":12600,"_vc":15},{"_i":"ms_012700.jpg","_t":12700,"_vc":48},{"_i":"ms_012800.jpg","_t":12800,"_vc":49},{"_i":"ms_012900.jpg","_t":12900,"_vc":49},{"_i":"ms_013100.jpg","_t":13100,"_vc":49},{"_i":"ms_013200.jpg","_t":13200,"_vc":49},{"_i":"ms_013300.jpg","_t":13300,"_vc":49},{"_i":"ms_013400.jpg","_t":13400,"_vc":49},{"_i":"ms_013500.jpg","_t":13500,"_vc":49},{"_i":"ms_013900.jpg","_t":13900,"_vc":49},{"_i":"ms_014000.jpg","_t":14000,"_vc":100}]],"visualComplete":[14000],"lighthouse":[31],"pagespeed":[78]}}