{"_ts":[1519893988,1519937875,1519981975],"_r":{"breakdown":{"html":{"bytes":[18860,18140,18130],"requests":[2,1,1]},"js":{"bytes":[235592,235602,235594],"requests":[18,18,18]},"css":{"bytes":[79554,79554,79554],"requests":[7,7,7]},"image":{"bytes":[467324,467324,467324],"requests":[13,13,13]},"flash":{"bytes":[0,0,0],"requests":[0,0,0]},"font":{"bytes":[149051,149051,149051],"requests":[5,5,5]},"video":{"bytes":[0,0,0],"requests":[0,0,0]},"other":{"bytes":[0,0,0],"requests":[0,0,0]}},"date":[1519893988,1519937875,1519981975],"domElements":[1528,1527,1527],"domInteractive":[8815,6869,7418],"firstPaint":[6749.7000000003,6098.1000000029,6718.3999999979],"fullyLoaded":[9675,7822,8217],"id":["180301_YR_922adf10ae84eb046dcc4b557a8e66c8","180301_6Q_7b6ad4f617b282db90d884e4d68c8070","180302_C2_10c3b9677ed34ce8e234358eb5d96999"],"loadTime":[9618,7760,8160],"render":[6700,6100,6800],"SpeedIndex":[7361,6700,7319],"TTFB":[5435,4717,5243],"videoFrames":[[{"_i":"ms_000000.jpg","_t":0,"_vc":0},{"_i":"ms_006700.jpg","_t":6700,"_vc":18},{"_i":"ms_006900.jpg","_t":6900,"_vc":24},{"_i":"ms_007000.jpg","_t":7000,"_vc":33},{"_i":"ms_007100.jpg","_t":7100,"_vc":33},{"_i":"ms_007200.jpg","_t":7200,"_vc":34},{"_i":"ms_007300.jpg","_t":7300,"_vc":37},{"_i":"ms_007400.jpg","_t":7400,"_vc":87},{"_i":"ms_007600.jpg","_t":7600,"_vc":92},{"_i":"ms_009200.jpg","_t":9200,"_vc":96},{"_i":"ms_009300.jpg","_t":9300,"_vc":100},{"_i":"ms_009800.jpg","_t":9800,"_vc":100}],[{"_i":"ms_000000.jpg","_t":0,"_vc":0},{"_i":"ms_006100.jpg","_t":6100,"_vc":18},{"_i":"ms_006300.jpg","_t":6300,"_vc":33},{"_i":"ms_006500.jpg","_t":6500,"_vc":35},{"_i":"ms_006600.jpg","_t":6600,"_vc":37},{"_i":"ms_006900.jpg","_t":6900,"_vc":92},{"_i":"ms_007200.jpg","_t":7200,"_vc":92},{"_i":"ms_007400.jpg","_t":7400,"_vc":92},{"_i":"ms_007500.jpg","_t":7500,"_vc":100},{"_i":"ms_008000.jpg","_t":8000,"_vc":100},{"_i":"ms_008100.jpg","_t":8100,"_vc":100}],[{"_i":"ms_000000.jpg","_t":0,"_vc":0},{"_i":"ms_006800.jpg","_t":6800,"_vc":34},{"_i":"ms_006900.jpg","_t":6900,"_vc":33},{"_i":"ms_007100.jpg","_t":7100,"_vc":35},{"_i":"ms_007200.jpg","_t":7200,"_vc":36},{"_i":"ms_007300.jpg","_t":7300,"_vc":41},{"_i":"ms_007500.jpg","_t":7500,"_vc":44},{"_i":"ms_007600.jpg","_t":7600,"_vc":92},{"_i":"ms_007700.jpg","_t":7700,"_vc":92},{"_i":"ms_007800.jpg","_t":7800,"_vc":100},{"_i":"ms_008300.jpg","_t":8300,"_vc":100},{"_i":"ms_008400.jpg","_t":8400,"_vc":100}]],"visualComplete":[9300,7500,7800],"lighthouse":[54,54,54],"pagespeed":[68,68,67]}}