{"_ts":[1517450608,1517537901,1517711249,1517797894],"_r":{"breakdown":{"html":{"bytes":[43440,30705,45658,30770],"requests":[2,2,2,2]},"js":{"bytes":[1234365,990122,1205432,1135918],"requests":[42,35,42,42]},"css":{"bytes":[190584,153752,75426,81553],"requests":[5,5,4,5]},"image":{"bytes":[773527,642044,793540,774884],"requests":[39,37,39,39]},"flash":{"bytes":[0,0,0,0],"requests":[0,0,0,0]},"font":{"bytes":[169688,247759,146306,167601],"requests":[4,4,4,4]},"video":{"bytes":[0,0,0,0],"requests":[0,0,0,0]},"other":{"bytes":[16094,13375,16034,16816],"requests":[6,10,6,8]}},"date":[1517450608,1517537901,1517711249,1517797894],"domElements":[1302,1298,1302,1302],"domInteractive":[5439,21463,5726,5804],"firstPaint":[6086.0000001267,8161.200000206,6635.8000000473,6448.4000001103],"fullyLoaded":[10587,22520,10897,10945],"id":["180201_K1_1c0c28d1727cb070383e573d47788f5d","180202_3J_fff92fb2530f088f8d9d9ec7d4d62dca","180204_B5_e825daa42f07219357bb91cf6584cefa","180205_PJ_ee4db52ac4fb4217a2626f2da58759a1"],"loadTime":[7781,22307,7723,8187],"render":[6100,8200,6700,6400],"SpeedIndex":[6121,8559,6719,7152],"TTFB":[4352,6145,4565,4779],"videoFrames":[[{"_i":"ms_000000.jpg","_t":0,"_vc":0},{"_i":"ms_006100.jpg","_t":6100,"_vc":96},{"_i":"ms_006200.jpg","_t":6200,"_vc":98},{"_i":"ms_006300.jpg","_t":6300,"_vc":98},{"_i":"ms_006400.jpg","_t":6400,"_vc":99},{"_i":"ms_006800.jpg","_t":6800,"_vc":99},{"_i":"ms_006900.jpg","_t":6900,"_vc":99},{"_i":"ms_007700.jpg","_t":7700,"_vc":100},{"_i":"ms_008200.jpg","_t":8200,"_vc":100},{"_i":"ms_008300.jpg","_t":8300,"_vc":100}],[{"_i":"ms_000000.jpg","_t":0,"_vc":0},{"_i":"ms_008200.jpg","_t":8200,"_vc":9},{"_i":"ms_008300.jpg","_t":8300,"_vc":97},{"_i":"ms_008500.jpg","_t":8500,"_vc":97},{"_i":"ms_008700.jpg","_t":8700,"_vc":98},{"_i":"ms_008800.jpg","_t":8800,"_vc":97},{"_i":"ms_008900.jpg","_t":8900,"_vc":97},{"_i":"ms_009000.jpg","_t":9000,"_vc":98},{"_i":"ms_010200.jpg","_t":10200,"_vc":98},{"_i":"ms_010500.jpg","_t":10500,"_vc":98},{"_i":"ms_011500.jpg","_t":11500,"_vc":98},{"_i":"ms_012500.jpg","_t":12500,"_vc":98},{"_i":"ms_012700.jpg","_t":12700,"_vc":98},{"_i":"ms_015001.jpg","_t":15001,"_vc":98},{"_i":"ms_015200.jpg","_t":15200,"_vc":98},{"_i":"ms_017500.jpg","_t":17500,"_vc":98},{"_i":"ms_017700.jpg","_t":17700,"_vc":98},{"_i":"ms_021400.jpg","_t":21400,"_vc":100},{"_i":"ms_021500.jpg","_t":21500,"_vc":100},{"_i":"ms_021700.jpg","_t":21700,"_vc":100},{"_i":"ms_021800.jpg","_t":21800,"_vc":100},{"_i":"ms_021900.jpg","_t":21900,"_vc":100},{"_i":"ms_022300.jpg","_t":22300,"_vc":100},{"_i":"ms_022400.jpg","_t":22400,"_vc":100}],[{"_i":"ms_000000.jpg","_t":0,"_vc":0},{"_i":"ms_006700.jpg","_t":6700,"_vc":96},{"_i":"ms_006900.jpg","_t":6900,"_vc":99},{"_i":"ms_007000.jpg","_t":7000,"_vc":99},{"_i":"ms_007200.jpg","_t":7200,"_vc":99},{"_i":"ms_007400.jpg","_t":7400,"_vc":99},{"_i":"ms_008000.jpg","_t":8000,"_vc":100},{"_i":"ms_008400.jpg","_t":8400,"_vc":100}],[{"_i":"ms_000000.jpg","_t":0,"_vc":0},{"_i":"ms_006400.jpg","_t":6400,"_vc":18},{"_i":"ms_006500.jpg","_t":6500,"_vc":18},{"_i":"ms_006900.jpg","_t":6900,"_vc":18},{"_i":"ms_007300.jpg","_t":7300,"_vc":96},{"_i":"ms_007400.jpg","_t":7400,"_vc":97},{"_i":"ms_007600.jpg","_t":7600,"_vc":99},{"_i":"ms_007800.jpg","_t":7800,"_vc":99},{"_i":"ms_008000.jpg","_t":8000,"_vc":100},{"_i":"ms_008200.jpg","_t":8200,"_vc":100},{"_i":"ms_008600.jpg","_t":8600,"_vc":100},{"_i":"ms_008700.jpg","_t":8700,"_vc":100}]],"visualComplete":[7700,21400,8000,8000],"lighthouse":[36,36,36,36],"pagespeed":[62,62,62,61]}}