{"_ts":[1512125831,1512169591,1512213693],"_r":{"breakdown":{"html":{"bytes":[14657,14834,14834],"requests":[1,1,1]},"js":{"bytes":[627176,605812,605861],"requests":[23,22,22]},"css":{"bytes":[58344,58419,58344],"requests":[6,6,6]},"image":{"bytes":[2107891,2083398,2083398],"requests":[29,19,19]},"flash":{"bytes":[0,0,0],"requests":[0,0,0]},"font":{"bytes":[149051,149051,149051],"requests":[5,5,5]},"video":{"bytes":[0,0,0],"requests":[0,0,0]},"other":{"bytes":[0,0,0],"requests":[0,0,0]}},"date":[1512125831,1512169591,1512213693],"domElements":[1528,1532,1532],"domInteractive":[12788,24627,22256],"firstPaint":[8375,19837,15687],"fullyLoaded":[18640,30248,28142],"id":["171201_CE_47265b32607e1528937aff678a812868","171201_SG_9533c48f4424b2f802b73cf4fe97c3b2","171202_81_8118c928395c1aee1f0f61899982bf49"],"loadTime":[17203,27905,25809],"render":[8591,19903,15855],"SpeedIndex":[11130,23836,20992],"TTFB":[6600,13392,13840],"videoFrames":[[{"_i":"frame_0000.jpg","_t":0,"_vc":0},{"_i":"frame_0086.jpg","_t":8600,"_vc":28},{"_i":"frame_0092.jpg","_t":9200,"_vc":29},{"_i":"frame_0103.jpg","_t":10300,"_vc":30},{"_i":"frame_0110.jpg","_t":11000,"_vc":31},{"_i":"frame_0112.jpg","_t":11200,"_vc":37},{"_i":"frame_0119.jpg","_t":11900,"_vc":87},{"_i":"frame_0123.jpg","_t":12300,"_vc":87},{"_i":"frame_0125.jpg","_t":12500,"_vc":90},{"_i":"frame_0127.jpg","_t":12700,"_vc":90},{"_i":"frame_0128.jpg","_t":12800,"_vc":90},{"_i":"frame_0134.jpg","_t":13400,"_vc":90},{"_i":"frame_0136.jpg","_t":13600,"_vc":90},{"_i":"frame_0137.jpg","_t":13700,"_vc":90},{"_i":"frame_0139.jpg","_t":13900,"_vc":90},{"_i":"frame_0140.jpg","_t":14000,"_vc":90},{"_i":"frame_0142.jpg","_t":14200,"_vc":100}],[{"_i":"frame_0000.jpg","_t":0,"_vc":0},{"_i":"frame_0199.jpg","_t":19900,"_vc":28},{"_i":"frame_0221.jpg","_t":22100,"_vc":30},{"_i":"frame_0223.jpg","_t":22300,"_vc":30},{"_i":"frame_0237.jpg","_t":23700,"_vc":34},{"_i":"frame_0238.jpg","_t":23800,"_vc":34},{"_i":"frame_0243.jpg","_t":24300,"_vc":35},{"_i":"frame_0251.jpg","_t":25100,"_vc":35},{"_i":"frame_0255.jpg","_t":25500,"_vc":92},{"_i":"frame_0262.jpg","_t":26200,"_vc":100}],[{"_i":"frame_0000.jpg","_t":0,"_vc":0},{"_i":"frame_0159.jpg","_t":15900,"_vc":28},{"_i":"frame_0169.jpg","_t":16900,"_vc":29},{"_i":"frame_0171.jpg","_t":17100,"_vc":30},{"_i":"frame_0184.jpg","_t":18400,"_vc":30},{"_i":"frame_0205.jpg","_t":20500,"_vc":34},{"_i":"frame_0207.jpg","_t":20700,"_vc":34},{"_i":"frame_0215.jpg","_t":21500,"_vc":34},{"_i":"frame_0218.jpg","_t":21800,"_vc":34},{"_i":"frame_0219.jpg","_t":21900,"_vc":34},{"_i":"frame_0221.jpg","_t":22100,"_vc":35},{"_i":"frame_0227.jpg","_t":22700,"_vc":35},{"_i":"frame_0231.jpg","_t":23100,"_vc":88},{"_i":"frame_0240.jpg","_t":24000,"_vc":97},{"_i":"frame_0252.jpg","_t":25200,"_vc":100}]],"visualComplete":[14200,26200,25200],"lighthouse":[null,null,null],"pagespeed":[26,32,36]}}