{"_ts":[1509496997],"_r":{"breakdown":{"html":{"bytes":[3854],"requests":[6]},"js":{"bytes":[809177],"requests":[33]},"css":{"bytes":[397598],"requests":[9]},"image":{"bytes":[3994494],"requests":[85]},"flash":{"bytes":[0],"requests":[0]},"font":{"bytes":[198988],"requests":[8]},"video":{"bytes":[4506682],"requests":[2]},"other":{"bytes":[20355],"requests":[4]}},"date":[1509496997],"domElements":[2156],"domInteractive":[15463],"firstPaint":[9414],"fullyLoaded":[31446.5],"id":["171101_2F_c29b779b4863de2962a7c91aceba5c4f"],"loadTime":[23676.5],"render":[9531],"SpeedIndex":[18239],"TTFB":[6671],"videoFrames":[[{"_i":"frame_0000.jpg","_t":0,"_vc":0},{"_i":"frame_0110.jpg","_t":11000,"_vc":5},{"_i":"frame_0112.jpg","_t":11200,"_vc":6},{"_i":"frame_0114.jpg","_t":11400,"_vc":6},{"_i":"frame_0116.jpg","_t":11600,"_vc":6},{"_i":"frame_0117.jpg","_t":11700,"_vc":6},{"_i":"frame_0141.jpg","_t":14100,"_vc":19},{"_i":"frame_0157.jpg","_t":15700,"_vc":26},{"_i":"frame_0166.jpg","_t":16600,"_vc":32},{"_i":"frame_0177.jpg","_t":17700,"_vc":35},{"_i":"frame_0186.jpg","_t":18600,"_vc":40},{"_i":"frame_0197.jpg","_t":19700,"_vc":45},{"_i":"frame_0207.jpg","_t":20700,"_vc":50},{"_i":"frame_0216.jpg","_t":21600,"_vc":57},{"_i":"frame_0227.jpg","_t":22700,"_vc":65},{"_i":"frame_0237.jpg","_t":23700,"_vc":73},{"_i":"frame_0246.jpg","_t":24600,"_vc":84},{"_i":"frame_0257.jpg","_t":25700,"_vc":94},{"_i":"frame_0266.jpg","_t":26600,"_vc":99},{"_i":"frame_0275.jpg","_t":27500,"_vc":100}]],"visualComplete":[22350],"lighthouse":[null],"pagespeed":[37]}}